enimda.py
enimda/__init__.py
enimda-2.1.0.dist-info/DESCRIPTION.rst
enimda-2.1.0.dist-info/METADATA
enimda-2.1.0.dist-info/RECORD
enimda-2.1.0.dist-info/WHEEL
enimda-2.1.0.dist-info/metadata.json
enimda-2.1.0.dist-info/top_level.txt
