Metadata-Version: 2.0
Name: enimda
Version: 2.1.0
Summary: Entropy-based image border detection algorithm library
Home-page: https://github.com/embali/enimda/
Author: Anton Smolin
Author-email: smolin.anton@gmail.com
License: MIT
Keywords: image border whitespace detection algorithm enimda entropy
Platform: UNKNOWN
Classifier: Development Status :: 5 - Production/Stable
Classifier: Intended Audience :: Developers
Classifier: License :: OSI Approved :: MIT License
Classifier: Programming Language :: Python :: 3.5
Classifier: Programming Language :: Python :: 3.6
Requires-Dist: imgpy (>=1.1.0)
Requires-Dist: numpy (>=1.12.1)
